{
  "assetName": "BTC/USD",
  "recordCount": 16389,
  "periodStart": "2026-04-04T09:00:06.629Z",
  "periodEnd": "2026-05-31T10:27:57.805Z",
  "hourCoverage": "7時間帯（0, 18, 19, 20, 21, 22, 23時）",
  "hourDistribution": [
    713,
    0,
    0,
    0,
    0,
    0,
    0,
    0,
    0,
    0,
    0,
    0,
    0,
    0,
    0,
    0,
    0,
    0,
    1985,
    2594,
    2775,
    2792,
    2927,
    2603
  ],
  "lastUpdated": "2026-06-02T23:13:51.034Z",
  "releaseFilename": "BTCUSD_20000.json.gz",
  "releaseFilePath": "/home/runner/work/theoption-trend-analyzer/theoption-trend-analyzer/.release-tmp/BTCUSD_20000.json.gz",
  "compressedSize": 55744848,
  "downloadUrl": "https://github.com/calpeshige/theoption-trend-analyzer/releases/download/data-BTCUSD-latest/BTCUSD_20000.json.gz"
}