{
  "assetName": "USD/JPY",
  "recordCount": 20000,
  "periodStart": "2026-06-15T02:04:34.633Z",
  "periodEnd": "2026-06-26T21:00:24.142Z",
  "hourCoverage": "全時間帯（0-23時）",
  "hourDistribution": [
    1215,
    838,
    545,
    499,
    510,
    413,
    36,
    1032,
    355,
    737,
    806,
    865,
    807,
    803,
    855,
    1051,
    1099,
    1061,
    1013,
    756,
    962,
    1178,
    1272,
    1292
  ],
  "lastUpdated": "2026-06-27T22:09:07.994Z",
  "releaseFilename": "USDJPY_20000.json.gz",
  "releaseFilePath": "/home/runner/work/theoption-trend-analyzer/theoption-trend-analyzer/.release-tmp/USDJPY_20000.json.gz",
  "compressedSize": 71672402,
  "downloadUrl": "https://github.com/calpeshige/theoption-trend-analyzer/releases/download/data-USDJPY-latest/USDJPY_20000.json.gz"
}