{
  "assetName": "USD/JPY",
  "recordCount": 15218,
  "periodStart": "2026-06-03T14:32:38.415Z",
  "periodEnd": "2026-07-06T20:51:24.409Z",
  "hourCoverage": "10時間帯（4, 5, 16, 17, 18, 19, 20, 21, 22, 23時）",
  "hourDistribution": [
    0,
    0,
    0,
    0,
    18,
    44,
    0,
    0,
    0,
    0,
    0,
    0,
    0,
    0,
    0,
    0,
    35,
    195,
    342,
    119,
    3021,
    4421,
    3619,
    3404
  ],
  "lastUpdated": "2026-07-09T22:23:30.666Z",
  "releaseFilename": "USDJPY_20000.json.gz",
  "releaseFilePath": "/home/runner/work/theoption-trend-analyzer/theoption-trend-analyzer/.release-tmp/USDJPY_20000.json.gz",
  "compressedSize": 52650496,
  "downloadUrl": "https://github.com/calpeshige/theoption-trend-analyzer/releases/download/data-USDJPY-latest/USDJPY_20000.json.gz"
}